contact_map/__init__.py
contact_map/_installed_version.py
contact_map/_version.py
contact_map/atom_indexer.py
contact_map/concurrence.py
contact_map/contact_count.py
contact_map/contact_map.py
contact_map/contact_trajectory.py
contact_map/dask_runner.py
contact_map/fix_parameters.py
contact_map/frequency_task.py
contact_map/min_dist.py
contact_map/plot_utils.py
contact_map/py_2_3.py
contact_map/topology.py
contact_map/version.py
contact_map/tests/__init__.py
contact_map/tests/concurrence.pdb
contact_map/tests/test_concurrence.py
contact_map/tests/test_contact_count.py
contact_map/tests/test_contact_map.py
contact_map/tests/test_contact_trajectory.py
contact_map/tests/test_dask_runner.py
contact_map/tests/test_frequency_task.py
contact_map/tests/test_min_dist.py
contact_map/tests/test_plot_utils.py
contact_map/tests/trajectory.pdb
contact_map/tests/utils.py
contact_map-0.7.0.dist-info/LICENSE
contact_map-0.7.0.dist-info/METADATA
contact_map-0.7.0.dist-info/WHEEL
contact_map-0.7.0.dist-info/top_level.txt
contact_map-0.7.0.dist-info/RECORD
