Metadata-Version: 2.1
Name: contact-map
Version: 0.7.0
Summary: Contact maps based on MDTraj
Home-page: https://github.com/dwhswenson/contact_map
Author: David W.H. Swenson and Sander Roet
Author-email: dwhs@hyperblazer.net, sanderroet@hotmail.com
License: LGPL 2.1+
Platform: UNKNOWN
Classifier: Development Status :: 4 - Beta
Classifier: Intended Audience :: Science/Research
Classifier: License :: OSI Approved :: GNU General Public License v2 or later (GPLv2+)
Classifier: Operating System :: POSIX
Classifier: Operating System :: Microsoft :: Windows
Classifier: Programming Language :: Python :: 2.7
Classifier: Programming Language :: Python :: 3
Classifier: Topic :: Scientific/Engineering :: Bio-Informatics
Classifier: Topic :: Scientific/Engineering :: Chemistry
Requires-Dist: future
Requires-Dist: numpy
Requires-Dist: mdtraj
Requires-Dist: scipy
Requires-Dist: pandas
